traceanalyzer.py
traceanalyzer-1.0.4.dist-info/METADATA
traceanalyzer-1.0.4.dist-info/RECORD
traceanalyzer-1.0.4.dist-info/WHEEL
traceanalyzer-1.0.4.dist-info/top_level.txt
